odoo/addons/product_uom_po_domain/README.rst
odoo/addons/product_uom_po_domain/__init__.py
odoo/addons/product_uom_po_domain/__manifest__.py
odoo/addons/product_uom_po_domain/demo/res_groups.xml
odoo/addons/product_uom_po_domain/i18n/fr.po
odoo/addons/product_uom_po_domain/i18n/product_uom_po_domain.pot
odoo/addons/product_uom_po_domain/models/__init__.py
odoo/addons/product_uom_po_domain/models/product_template.py
odoo/addons/product_uom_po_domain/readme/CONTRIBUTORS.rst
odoo/addons/product_uom_po_domain/readme/DESCRIPTION.rst
odoo/addons/product_uom_po_domain/readme/DEVELOP.rst
odoo/addons/product_uom_po_domain/static/description/icon.png
odoo/addons/product_uom_po_domain/static/description/index.html
odoo/addons/product_uom_po_domain/static/description/with_module.png
odoo/addons/product_uom_po_domain/static/description/without_module.png
odoo/addons/product_uom_po_domain/views/view_product_template.xml
odoo12_addon_product_uom_po_domain-12.0.1.0.2.dist-info/METADATA
odoo12_addon_product_uom_po_domain-12.0.1.0.2.dist-info/WHEEL
odoo12_addon_product_uom_po_domain-12.0.1.0.2.dist-info/top_level.txt
odoo12_addon_product_uom_po_domain-12.0.1.0.2.dist-info/RECORD
